Classfile /D:/workspace/projects/advance/learning/java-base/deep-in-java/stage-1/part-2-java-object-oriented-design/target/classes/com/jinm/deepinjava/objectoriented/design/CountingEnum.class
  Last modified 2020-2-26; size 1295 bytes
  MD5 checksum 9960b023e56da0a40bb2695a5e4098ce
  Compiled from "EnumClassDemo.java"
final class com.jinm.deepinjava.objectoriented.design.CountingEnum extends java.lang.Enum<com.jinm.deepinjava.objectoriented.design.CountingEnum>
  minor version: 0
  major version: 52
  flags: ACC_FINAL, ACC_SUPER, ACC_ENUM
Constant pool:
   #1 = Fieldref           #4.#45         // com/jinm/deepinjava/objectoriented/design/CountingEnum.$VALUES:[Lcom/jinm/deepinjava/objectoriented/design/CountingEnum;
   #2 = Methodref          #46.#47        // "[Lcom/jinm/deepinjava/objectoriented/design/CountingEnum;".clone:()Ljava/lang/Object;
   #3 = Class              #26            // "[Lcom/jinm/deepinjava/objectoriented/design/CountingEnum;"
   #4 = Class              #48            // com/jinm/deepinjava/objectoriented/design/CountingEnum
   #5 = Methodref          #18.#49        // java/lang/Enum.valueOf:(Ljava/lang/Class;Ljava/lang/String;)Ljava/lang/Enum;
   #6 = Methodref          #18.#50        // java/lang/Enum."<init>":(Ljava/lang/String;I)V
   #7 = String             #19            // ONE
   #8 = Methodref          #4.#50         // com/jinm/deepinjava/objectoriented/design/CountingEnum."<init>":(Ljava/lang/String;I)V
   #9 = Fieldref           #4.#51         // com/jinm/deepinjava/objectoriented/design/CountingEnum.ONE:Lcom/jinm/deepinjava/objectoriented/design/CountingEnum;
  #10 = String             #21            // TWO
  #11 = Fieldref           #4.#52         // com/jinm/deepinjava/objectoriented/design/CountingEnum.TWO:Lcom/jinm/deepinjava/objectoriented/design/CountingEnum;
  #12 = String             #22            // THREE
  #13 = Fieldref           #4.#53         // com/jinm/deepinjava/objectoriented/design/CountingEnum.THREE:Lcom/jinm/deepinjava/objectoriented/design/CountingEnum;
  #14 = String             #23            // FOUR
  #15 = Fieldref           #4.#54         // com/jinm/deepinjava/objectoriented/design/CountingEnum.FOUR:Lcom/jinm/deepinjava/objectoriented/design/CountingEnum;
  #16 = String             #24            // FIVE
  #17 = Fieldref           #4.#55         // com/jinm/deepinjava/objectoriented/design/CountingEnum.FIVE:Lcom/jinm/deepinjava/objectoriented/design/CountingEnum;
  #18 = Class              #56            // java/lang/Enum
  #19 = Utf8               ONE
  #20 = Utf8               Lcom/jinm/deepinjava/objectoriented/design/CountingEnum;
  #21 = Utf8               TWO
  #22 = Utf8               THREE
  #23 = Utf8               FOUR
  #24 = Utf8               FIVE
  #25 = Utf8               $VALUES
  #26 = Utf8               [Lcom/jinm/deepinjava/objectoriented/design/CountingEnum;
  #27 = Utf8               values
  #28 = Utf8               ()[Lcom/jinm/deepinjava/objectoriented/design/CountingEnum;
  #29 = Utf8               Code
  #30 = Utf8               LineNumberTable
  #31 = Utf8               valueOf
  #32 = Utf8               (Ljava/lang/String;)Lcom/jinm/deepinjava/objectoriented/design/CountingEnum;
  #33 = Utf8               LocalVariableTable
  #34 = Utf8               name
  #35 = Utf8               Ljava/lang/String;
  #36 = Utf8               <init>
  #37 = Utf8               (Ljava/lang/String;I)V
  #38 = Utf8               this
  #39 = Utf8               Signature
  #40 = Utf8               ()V
  #41 = Utf8               <clinit>
  #42 = Utf8               Ljava/lang/Enum<Lcom/jinm/deepinjava/objectoriented/design/CountingEnum;>;
  #43 = Utf8               SourceFile
  #44 = Utf8               EnumClassDemo.java
  #45 = NameAndType        #25:#26        // $VALUES:[Lcom/jinm/deepinjava/objectoriented/design/CountingEnum;
  #46 = Class              #26            // "[Lcom/jinm/deepinjava/objectoriented/design/CountingEnum;"
  #47 = NameAndType        #57:#58        // clone:()Ljava/lang/Object;
  #48 = Utf8               com/jinm/deepinjava/objectoriented/design/CountingEnum
  #49 = NameAndType        #31:#59        // valueOf:(Ljava/lang/Class;Ljava/lang/String;)Ljava/lang/Enum;
  #50 = NameAndType        #36:#37        // "<init>":(Ljava/lang/String;I)V
  #51 = NameAndType        #19:#20        // ONE:Lcom/jinm/deepinjava/objectoriented/design/CountingEnum;
  #52 = NameAndType        #21:#20        // TWO:Lcom/jinm/deepinjava/objectoriented/design/CountingEnum;
  #53 = NameAndType        #22:#20        // THREE:Lcom/jinm/deepinjava/objectoriented/design/CountingEnum;
  #54 = NameAndType        #23:#20        // FOUR:Lcom/jinm/deepinjava/objectoriented/design/CountingEnum;
  #55 = NameAndType        #24:#20        // FIVE:Lcom/jinm/deepinjava/objectoriented/design/CountingEnum;
  #56 = Utf8               java/lang/Enum
  #57 = Utf8               clone
  #58 = Utf8               ()Ljava/lang/Object;
  #59 = Utf8               (Ljava/lang/Class;Ljava/lang/String;)Ljava/lang/Enum;
{
  public static final com.jinm.deepinjava.objectoriented.design.CountingEnum ONE;
    descriptor: Lcom/jinm/deepinjava/objectoriented/design/CountingEnum;
    flags: ACC_PUBLIC, ACC_STATIC, ACC_FINAL, ACC_ENUM

  public static final com.jinm.deepinjava.objectoriented.design.CountingEnum TWO;
    descriptor: Lcom/jinm/deepinjava/objectoriented/design/CountingEnum;
    flags: ACC_PUBLIC, ACC_STATIC, ACC_FINAL, ACC_ENUM

  public static final com.jinm.deepinjava.objectoriented.design.CountingEnum THREE;
    descriptor: Lcom/jinm/deepinjava/objectoriented/design/CountingEnum;
    flags: ACC_PUBLIC, ACC_STATIC, ACC_FINAL, ACC_ENUM

  public static final com.jinm.deepinjava.objectoriented.design.CountingEnum FOUR;
    descriptor: Lcom/jinm/deepinjava/objectoriented/design/CountingEnum;
    flags: ACC_PUBLIC, ACC_STATIC, ACC_FINAL, ACC_ENUM

  public static final com.jinm.deepinjava.objectoriented.design.CountingEnum FIVE;
    descriptor: Lcom/jinm/deepinjava/objectoriented/design/CountingEnum;
    flags: ACC_PUBLIC, ACC_STATIC, ACC_FINAL, ACC_ENUM

  public static com.jinm.deepinjava.objectoriented.design.CountingEnum[] values();
    descriptor: ()[Lcom/jinm/deepinjava/objectoriented/design/CountingEnum;
    flags: ACC_PUBLIC, ACC_STATIC
    Code:
      stack=1, locals=0, args_size=0
         0: getstatic     #1                  // Field $VALUES:[Lcom/jinm/deepinjava/objectoriented/design/CountingEnum;
         3: invokevirtual #2                  // Method "[Lcom/jinm/deepinjava/objectoriented/design/CountingEnum;".clone:()Ljava/lang/Object;
         6: checkcast     #3                  // class "[Lcom/jinm/deepinjava/objectoriented/design/CountingEnum;"
         9: areturn
      LineNumberTable:
        line 63: 0

  public static com.jinm.deepinjava.objectoriented.design.CountingEnum valueOf(java.lang.String);
    descriptor: (Ljava/lang/String;)Lcom/jinm/deepinjava/objectoriented/design/CountingEnum;
    flags: ACC_PUBLIC, ACC_STATIC
    Code:
      stack=2, locals=1, args_size=1
         0: ldc           #4                  // class com/jinm/deepinjava/objectoriented/design/CountingEnum
         2: aload_0
         3: invokestatic  #5                  // Method java/lang/Enum.valueOf:(Ljava/lang/Class;Ljava/lang/String;)Ljava/lang/Enum;
         6: checkcast     #4                  // class com/jinm/deepinjava/objectoriented/design/CountingEnum
         9: areturn
      LineNumberTable:
        line 63: 0
      LocalVariableTable:
        Start  Length  Slot  Name   Signature
            0      10     0  name   Ljava/lang/String;

  static {};
    descriptor: ()V
    flags: ACC_STATIC
    Code:
      stack=4, locals=0, args_size=0
         0: new           #4                  // class com/jinm/deepinjava/objectoriented/design/CountingEnum
         3: dup
         4: ldc           #7                  // String ONE
         6: iconst_0
         7: invokespecial #8                  // Method "<init>":(Ljava/lang/String;I)V
        10: putstatic     #9                  // Field ONE:Lcom/jinm/deepinjava/objectoriented/design/CountingEnum;
        13: new           #4                  // class com/jinm/deepinjava/objectoriented/design/CountingEnum
        16: dup
        17: ldc           #10                 // String TWO
        19: iconst_1
        20: invokespecial #8                  // Method "<init>":(Ljava/lang/String;I)V
        23: putstatic     #11                 // Field TWO:Lcom/jinm/deepinjava/objectoriented/design/CountingEnum;
        26: new           #4                  // class com/jinm/deepinjava/objectoriented/design/CountingEnum
        29: dup
        30: ldc           #12                 // String THREE
        32: iconst_2
        33: invokespecial #8                  // Method "<init>":(Ljava/lang/String;I)V
        36: putstatic     #13                 // Field THREE:Lcom/jinm/deepinjava/objectoriented/design/CountingEnum;
        39: new           #4                  // class com/jinm/deepinjava/objectoriented/design/CountingEnum
        42: dup
        43: ldc           #14                 // String FOUR
        45: iconst_3
        46: invokespecial #8                  // Method "<init>":(Ljava/lang/String;I)V
        49: putstatic     #15                 // Field FOUR:Lcom/jinm/deepinjava/objectoriented/design/CountingEnum;
        52: new           #4                  // class com/jinm/deepinjava/objectoriented/design/CountingEnum
        55: dup
        56: ldc           #16                 // String FIVE
        58: iconst_4
        59: invokespecial #8                  // Method "<init>":(Ljava/lang/String;I)V
        62: putstatic     #17                 // Field FIVE:Lcom/jinm/deepinjava/objectoriented/design/CountingEnum;
        65: iconst_5
        66: anewarray     #4                  // class com/jinm/deepinjava/objectoriented/design/CountingEnum
        69: dup
        70: iconst_0
        71: getstatic     #9                  // Field ONE:Lcom/jinm/deepinjava/objectoriented/design/CountingEnum;
        74: aastore
        75: dup
        76: iconst_1
        77: getstatic     #11                 // Field TWO:Lcom/jinm/deepinjava/objectoriented/design/CountingEnum;
        80: aastore
        81: dup
        82: iconst_2
        83: getstatic     #13                 // Field THREE:Lcom/jinm/deepinjava/objectoriented/design/CountingEnum;
        86: aastore
        87: dup
        88: iconst_3
        89: getstatic     #15                 // Field FOUR:Lcom/jinm/deepinjava/objectoriented/design/CountingEnum;
        92: aastore
        93: dup
        94: iconst_4
        95: getstatic     #17                 // Field FIVE:Lcom/jinm/deepinjava/objectoriented/design/CountingEnum;
        98: aastore
        99: putstatic     #1                  // Field $VALUES:[Lcom/jinm/deepinjava/objectoriented/design/CountingEnum;
       102: return
      LineNumberTable:
        line 66: 0
        line 67: 13
        line 68: 26
        line 69: 39
        line 70: 52
        line 63: 65
}
Signature: #42                          // Ljava/lang/Enum<Lcom/jinm/deepinjava/objectoriented/design/CountingEnum;>;
SourceFile: "EnumClassDemo.java"
